langchain_community/__init__.py
langchain_community/cache.py
langchain_community/py.typed
langchain_community/adapters/__init__.py
langchain_community/adapters/openai.py
langchain_community/agent_toolkits/__init__.py
langchain_community/agent_toolkits/azure_ai_services.py
langchain_community/agent_toolkits/azure_cognitive_services.py
langchain_community/agent_toolkits/base.py
langchain_community/agent_toolkits/load_tools.py
langchain_community/agent_toolkits/ainetwork/__init__.py
langchain_community/agent_toolkits/ainetwork/toolkit.py
langchain_community/agent_toolkits/amadeus/__init__.py
langchain_community/agent_toolkits/amadeus/toolkit.py
langchain_community/agent_toolkits/cassandra_database/__init__.py
langchain_community/agent_toolkits/cassandra_database/toolkit.py
langchain_community/agent_toolkits/clickup/__init__.py
langchain_community/agent_toolkits/clickup/toolkit.py
langchain_community/agent_toolkits/cogniswitch/__init__.py
langchain_community/agent_toolkits/cogniswitch/toolkit.py
langchain_community/agent_toolkits/connery/__init__.py
langchain_community/agent_toolkits/connery/toolkit.py
langchain_community/agent_toolkits/csv/__init__.py
langchain_community/agent_toolkits/file_management/__init__.py
langchain_community/agent_toolkits/file_management/toolkit.py
langchain_community/agent_toolkits/financial_datasets/__init__.py
langchain_community/agent_toolkits/financial_datasets/toolkit.py
langchain_community/agent_toolkits/github/__init__.py
langchain_community/agent_toolkits/github/toolkit.py
langchain_community/agent_toolkits/gitlab/__init__.py
langchain_community/agent_toolkits/gitlab/toolkit.py
langchain_community/agent_toolkits/gmail/__init__.py
langchain_community/agent_toolkits/gmail/toolkit.py
langchain_community/agent_toolkits/jira/__init__.py
langchain_community/agent_toolkits/jira/toolkit.py
langchain_community/agent_toolkits/json/__init__.py
langchain_community/agent_toolkits/json/base.py
langchain_community/agent_toolkits/json/prompt.py
langchain_community_aipy-0.3.11.dist-info/METADATA
langchain_community_aipy-0.3.11.dist-info/WHEEL
langchain_community_aipy-0.3.11.dist-info/top_level.txt
langchain_community_aipy-0.3.11.dist-info/RECORD
