Metadata-Version: 2.4
Name: langchain-community-aipy
Version: 0.3.11
Summary: Community contributed LangChain integrations.
Author-email: The QPYPI Team <qpypi@qpython.org>
License: MIT AND (Apache-2.0 OR BSD-2-Clause)
Project-URL: Homepage, https://qpypi.qpython.org/project/langchain-community-aipy/
Classifier: Intended Audience :: Developers
Classifier: Intended Audience :: Education
Classifier: Intended Audience :: Information Technology
Classifier: Intended Audience :: End Users/Desktop
Classifier: License :: OSI Approved :: Apache Software License
Classifier: Operating System :: Android
Classifier: Programming Language :: Python
Classifier: Programming Language :: Python :: 3.12
Classifier: Topic :: Software Development
Requires-Python: ==3.12.*
Requires-Dist: numpy-aipy
Requires-Dist: sqlalchemy-qpython
Requires-Dist: aiohttp-qpython
Requires-Dist: PyYAML
Requires-Dist: tenacity
Requires-Dist: dataclasses-json
Requires-Dist: httpx-sse
